skillpub/__init__.cpython-36m-darwin.so
skillpub/__init__.cpython-36m-x86_64-linux-gnu.so
skillpub/__init__.cpython-37m-darwin.so
skillpub/__init__.cpython-37m-x86_64-linux-gnu.so
skillpub/__init__.cpython-38-darwin.so
skillpub/__init__.py
skillpub/__main__.cpython-36m-darwin.so
skillpub/__main__.cpython-36m-x86_64-linux-gnu.so
skillpub/__main__.cpython-37m-darwin.so
skillpub/__main__.cpython-37m-x86_64-linux-gnu.so
skillpub/__main__.cpython-38-darwin.so
skillpub/__main__.py
skillpub/api.cpython-36m-darwin.so
skillpub/api.cpython-36m-x86_64-linux-gnu.so
skillpub/api.cpython-37m-darwin.so
skillpub/api.cpython-37m-x86_64-linux-gnu.so
skillpub/api.cpython-38-darwin.so
skillpub/bot.cpython-36m-darwin.so
skillpub/bot.cpython-36m-x86_64-linux-gnu.so
skillpub/bot.cpython-37m-darwin.so
skillpub/bot.cpython-37m-x86_64-linux-gnu.so
skillpub/bot.cpython-38-darwin.so
skillpub/brain.cpython-36m-darwin.so
skillpub/brain.cpython-36m-x86_64-linux-gnu.so
skillpub/brain.cpython-37m-darwin.so
skillpub/brain.cpython-37m-x86_64-linux-gnu.so
skillpub/brain.cpython-38-darwin.so
skillpub/config.cpython-36m-darwin.so
skillpub/config.cpython-36m-x86_64-linux-gnu.so
skillpub/config.cpython-37m-darwin.so
skillpub/config.cpython-37m-x86_64-linux-gnu.so
skillpub/config.cpython-38-darwin.so
skillpub/executor.cpython-36m-darwin.so
skillpub/executor.cpython-36m-x86_64-linux-gnu.so
skillpub/executor.cpython-37m-darwin.so
skillpub/executor.cpython-37m-x86_64-linux-gnu.so
skillpub/executor.cpython-38-darwin.so
skillpub/executor_proc.cpython-36m-darwin.so
skillpub/executor_proc.cpython-36m-x86_64-linux-gnu.so
skillpub/executor_proc.cpython-37m-darwin.so
skillpub/executor_proc.cpython-37m-x86_64-linux-gnu.so
skillpub/executor_proc.cpython-38-darwin.so
skillpub/executor_sched.cpython-36m-darwin.so
skillpub/executor_sched.cpython-36m-x86_64-linux-gnu.so
skillpub/executor_sched.cpython-37m-darwin.so
skillpub/executor_sched.cpython-37m-x86_64-linux-gnu.so
skillpub-0.2.90.dist-info/DESCRIPTION.rst
skillpub-0.2.90.dist-info/METADATA
skillpub-0.2.90.dist-info/RECORD
skillpub-0.2.90.dist-info/WHEEL
skillpub-0.2.90.dist-info/entry_points.txt
skillpub-0.2.90.dist-info/metadata.json
skillpub-0.2.90.dist-info/top_level.txt
